jrsync/__init__.py
jrsync/conf/__init__.py
jrsync/conf/global_settings.py
jrsync/conf/reader.py
jrsync/core/__init__.py
jrsync/core/main.py
jrsync/core/pid_control.py
jrsync/core/pyrsync.py
jrsync/management/__init__.py
jrsync/management/cli.py
jrsync/model/__init__.py
jrsync/model/sync.py
jrsync/utils/__init__.py
jrsync/utils/log.py
jrsync/utils/module_loading.py
jrsync/utils/str_parser.py
jrsync/utils/str_validator.py
jrsync/utils/timelib.py
jrsync-0.1.7.dist-info/LICENSE
jrsync-0.1.7.dist-info/METADATA
jrsync-0.1.7.dist-info/WHEEL
jrsync-0.1.7.dist-info/entry_points.txt
jrsync-0.1.7.dist-info/RECORD
