Metadata-Version: 2.1
Name: jrsync
Version: 0.1.7
Summary: JSON Configurable wrapper on unix rsync
Author: Antonio Mariani
Author-email: antonio.mariani@cmcc.it
Requires-Python: >=3.10,<4.0
Classifier: Programming Language :: Python :: 3
Classifier: Programming Language :: Python :: 3.10
Classifier: Programming Language :: Python :: 3.11
Classifier: Programming Language :: Python :: 3.12
Requires-Dist: pydantic (>=2.8.2,<3.0.0)
Requires-Dist: pytest (>=8.3.2,<9.0.0)
Requires-Dist: pyyaml (>=6.0.1,<7.0.0)
